momopapa/__init__.py
momopapa/cont.py
momopapa/db.py
momopapa/util.py
momopapa/bot/__init__.py
momopapa/bot/slack.py
momopapa/pandabase/__init__.py
momopapa/pandabase/companda.py
momopapa/pandabase/helpers.py
momopapa/pandabase/sql.py
momopapa/pandabase/util.py
momopapa_slim/__init__.py
momopapa_slim/db.py
momopapa_slim/bot/__init__.py
momopapa_slim/bot/slack.py
momopapa_slim/pandabase/__init__.py
momopapa_slim/pandabase/companda.py
momopapa_slim/pandabase/helpers.py
momopapa_slim/pandabase/sql.py
momopapa_slim/pandabase/util.py
momopapa_slim-1.0.2.dist-info/LICENSE
momopapa_slim-1.0.2.dist-info/METADATA
momopapa_slim-1.0.2.dist-info/WHEEL
momopapa_slim-1.0.2.dist-info/top_level.txt
momopapa_slim-1.0.2.dist-info/RECORD
