Metadata-Version: 2.1
Name: momopapa-slim
Version: 1.0.2
Summary: Bigdata Analysis Utilities
Home-page: https://github.com/jihokwak/motive
Author: momopapa
Author-email: datamanage@hellonature.net
License: UNKNOWN
Platform: UNKNOWN
Classifier: Programming Language :: Python :: 3
Classifier: License :: OSI Approved :: MIT License
Classifier: Operating System :: OS Independent
Requires-Python: >=3.7
Requires-Dist: botocore (==1.17.28)
Requires-Dist: certifi (==2020.6.20)
Requires-Dist: chardet (==3.0.4)
Requires-Dist: docutils (==0.15.2)
Requires-Dist: fsspec (==0.7.4)
Requires-Dist: idna (==2.10)
Requires-Dist: jmespath (==0.10.0)
Requires-Dist: numpy (==1.19.1)
Requires-Dist: pandas (==1.0.5)
Requires-Dist: psycopg2-binary (==2.8.5)
Requires-Dist: PyMySQL (==0.10.0)
Requires-Dist: python-dateutil (==2.8.1)
Requires-Dist: pytz (==2020.1)
Requires-Dist: requests (==2.24.0)
Requires-Dist: s3fs (==0.4.2)
Requires-Dist: six (==1.15.0)
Requires-Dist: slacker (==0.14.0)
Requires-Dist: SQLAlchemy (==1.3.18)
Requires-Dist: urllib3 (==1.25.10)
